server/__init__.py
server/server.py
server/common/__init__.py
server/common/config_startup.py
server/common/decos.py
server/common/descriptors.py
server/common/errors.py
server/common/metaclasses.py
server/common/utils.py
server/common/variables.py
server/logs/__init__.py
server/server/__init__.py
server/server/add_user.py
server/server/config_window.py
server/server/core.py
server/server/main_window.py
server/server/remove_user.py
server/server/server_db.py
server/server/stat_window.py
server/unit_tests/__init__.py
server/unit_tests/test_client.py
server/unit_tests/test_server.py
server/unit_tests/test_utils.py
server/unit_tests/test_valid.py
server_mess_proj-0.0.2.dist-info/METADATA
server_mess_proj-0.0.2.dist-info/WHEEL
server_mess_proj-0.0.2.dist-info/top_level.txt
server_mess_proj-0.0.2.dist-info/RECORD
