Metadata-Version: 2.1
Name: server-mess-proj
Version: 0.0.2
Summary: server_mess_proj
Home-page: UNKNOWN
Author: Ivan Ivanov
Author-email: volga52@bk.ru
License: UNKNOWN
Platform: UNKNOWN
Requires-Dist: PyQt5
Requires-Dist: sqlalchemy
Requires-Dist: pycryptodome
Requires-Dist: pycryptodomex
